tiny_2d_engine/__init__.py
tiny_2d_engine/acquisition_canvas.py
tiny_2d_engine/base_canvas_object.py
tiny_2d_engine/cli.py
tiny_2d_engine/color_utils.py
tiny_2d_engine/constants.py
tiny_2d_engine/forms.py
tiny_2d_engine/generic_widgets.py
tiny_2d_engine/loader.py
tiny_2d_engine/main.py
tiny_2d_engine/menus.py
tiny_2d_engine/popups.py
tiny_2d_engine/utils.py
tiny_2d_engine/images/load_icon.gif
tiny_2d_engine-0.0.0.dist-info/LICENSE.md
tiny_2d_engine-0.0.0.dist-info/METADATA
tiny_2d_engine-0.0.0.dist-info/WHEEL
tiny_2d_engine-0.0.0.dist-info/entry_points.txt
tiny_2d_engine-0.0.0.dist-info/top_level.txt
tiny_2d_engine-0.0.0.dist-info/RECORD
