Metadata-Version: 2.1
Name: tiny-2d-engine
Version: 0.0.0
Summary: 2D acquisition canvas
Home-page: https://nitrox.cerfacs.fr/open-source/tiny_2d_engine
Author: A. Dauptain, L. F. Pereira
Author-email: dauptain@cerfacs.fr
License: UNKNOWN
Project-URL: Homepage, https://nitrox.cerfacs.fr/open-source/tiny_2d_engine
Project-URL: Bug Tracker, https://nitrox.cerfacs.fr/open-source/tiny_2d_engine/issues
Keywords: gui,tkinter,reverse engineering,acquisition,geometry,image
Platform: UNKNOWN
Classifier: Programming Language :: Python :: 3.8
Classifier: Programming Language :: Python :: 3.9
Classifier: Programming Language :: Python :: 3.10
Classifier: License :: OSI Approved :: MIT License
Requires-Python: >=3.6
License-File: LICENSE.md
Requires-Dist: click
Requires-Dist: pillow
Requires-Dist: numpy
